{
    "os": "Linux-6.5.0-26-generic-x86_64-with-glibc2.35",
    "python": "3.10.12",
    "heartbeatAt": "2024-04-01T19:04:38.795423",
    "startedAt": "2024-04-01T19:04:37.637012",
    "docker": null,
    "cuda": null,
    "args": [],
    "state": "running",
    "program": "/home/sandeep/Documents/IITM/Deep Learning/Assignment 2/main.py",
    "codePathLocal": "main.py",
    "codePath": "main.py",
    "git": {
        "remote": "https://github.com/sandeepkumarsuresh/cs6910_assignment2.git",
        "commit": "eb670868ade6db00ecaf328494992a84a2fe5561"
    },
    "email": "sandeepsuresh619@gmail.com",
    "root": "/home/sandeep/Documents/IITM/Deep Learning/Assignment 2",
    "host": "sandeep-Inspiron-5415",
    "username": "sandeep",
    "executable": "/usr/bin/python3",
    "cpu_count": 6,
    "cpu_count_logical": 12,
    "cpu_freq": {
        "current": 2050.351,
        "min": 400.0,
        "max": 4056.0
    },
    "cpu_freq_per_core": [
        {
            "current": 2851.931,
            "min": 400.0,
            "max": 4056.0
        },
        {
            "current": 400.0,
            "min": 400.0,
            "max": 4056.0
        },
        {
            "current": 2275.486,
            "min": 400.0,
            "max": 4056.0
        },
        {
            "current": 400.0,
            "min": 400.0,
            "max": 4056.0
        },
        {
            "current": 3959.068,
            "min": 400.0,
            "max": 4056.0
        },
        {
            "current": 4035.652,
            "min": 400.0,
            "max": 4056.0
        },
        {
            "current": 400.0,
            "min": 400.0,
            "max": 4056.0
        },
        {
            "current": 2331.096,
            "min": 400.0,
            "max": 4056.0
        },
        {
            "current": 1721.208,
            "min": 400.0,
            "max": 4056.0
        },
        {
            "current": 1796.613,
            "min": 400.0,
            "max": 4056.0
        },
        {
            "current": 400.0,
            "min": 400.0,
            "max": 4056.0
        },
        {
            "current": 1688.379,
            "min": 400.0,
            "max": 4056.0
        }
    ],
    "disk": {
        "/": {
            "total": 27.33292007446289,
            "used": 16.272743225097656
        }
    },
    "memory": {
        "total": 7.103458404541016
    }
}
